stdgif/__init__.py
stdgif/stdgif.py
stdgif-0.1.0.dist-info/top_level.txt
stdgif-0.1.0.dist-info/entry_points.txt
stdgif-0.1.0.dist-info/METADATA
stdgif-0.1.0.dist-info/DESCRIPTION.rst
stdgif-0.1.0.dist-info/metadata.json
stdgif-0.1.0.dist-info/WHEEL
stdgif-0.1.0.dist-info/RECORD
